design.sv
// ALU design, positive clock edge triggred
/* opCodes and their functions
        0000	a+b;
        0001	a-b;
        0010	left shift a, a<<1;
        0011	right shift a, a>>1;
        0100	ring shift a left by 1;
        0101	ring shift a right by 1;
        0110	a AND b;
        0111	a OR b;
        1000	a XOR b;
        1001	equal
        1010	unused
        1011	unused
        1100	unused
        1101	unused
        1110	unused
        1111	unused
       
   unused opCodes can be suitably utilized for other
   operations, as per requirement
*/
module alu_8_bit(alu_out, carry_out, in_a, in_b, opCode, clk, rst);
  output reg [7:0]alu_out;
  output reg carry_out;
  input [7:0] in_a;
  input [7:0] in_b;
  input [3:0] opCode;
  input clk, rst;			//positive clock edge sensitive
  							//negative logic asynchronous reset	
  wire [7:0] add_out;
  wire [7:0] subt_out;
  wire [7:0] l_sh_out;
  wire [7:0] r_sh_out;
  wire [7:0] rng_l_out;
  wire [7:0] rng_r_out;
  wire [7:0] band_out;
  wire [7:0] bor_out;
  wire [7:0] bxor_out;
  wire [7:0] equl_out;
  
  wire [7:0] alu_out_temp;
  wire carry_temp;
  
  wire [9:0] carry;
  
  add_8_bit M0(add_out, carry[0], in_a, in_b);
  sub_8_bit M1(subt_out, carry[1], in_a, in_b);
  left_shft M2(l_sh_out, carry[2], in_a);
  right_shft M3(r_sh_out, carry[3], in_a);
  ring_lt M4(rng_l_out, carry[4], in_a);
  ring_rt M5(rng_r_out, carry[5], in_a);
  bitw_and M6(band_out, carry[6], in_a, in_b);
  bitw_or M7(bor_out, carry[7], in_a, in_b);
  bitw_xor M8(bxor_out, carry[8], in_a, in_b);
  equl M9(equl_out, carry[9], in_a, in_b);
  
  mux_8bit M10(alu_out_temp, opCode, add_out, subt_out, l_sh_out, r_sh_out, rng_l_out, rng_r_out, band_out, bor_out, bxor_out, equl_out, 8'b0, 8'b0, 8'b0, 8'b0, 8'b0, 8'b0);
  
  mux_1bit M11(carry_temp, opCode, carry[0], carry[1], carry[2], carry[3], carry[4], carry[5], carry[6], carry[7], carry[8], carry[9], 1'b0, 1'b0, 1'b0, 1'b0, 1'b0, 1'b0);
  
  always@(posedge clk, negedge rst) begin
    if(!rst) begin
      alu_out <= 8'b0;
      carry_out <= 1'b0;
    end
    else begin
      alu_out <= alu_out_temp;
      carry_out <= carry_temp;
    end
  end
  
endmodule

module add_8_bit(out, cr, in1, in2);		//8-bit adder
  output reg [7:0]out;
  output reg cr;
  input [7:0]in1;
  input [7:0]in2;
  reg [8:0] total;
  
  always@(*) begin
    total[8:0] <= in1 + in2;
    cr <= total[8];
    out[7:0] <= total[7:0];
  end
endmodule

module sub_8_bit(out, cr, in1, in2);		//8-bit subtractor
  output reg [7:0]out;
  output reg cr;
  input [7:0]in1;
  input [7:0]in2;
  
  reg [7:0]neg_in2;
  
  always@(*) begin
    neg_in2 <= ~(in2)+8'b00000001;
    out <= in1 + neg_in2;
    cr <= (in1>in2 || in1==in2)?0:1;
  end
endmodule


module left_shft(out, cr, in);		//left shifting operator
  output reg [7:0]out;
  output reg cr;
  input [7:0] in;
  
  always@(*) begin
    out[7:0] <= {in[6:0], 1'b0};
    cr <= 1'b0;
  end
endmodule

module right_shft(out, cr, in);		//right shifting operator
  output reg [7:0]out;
  output reg cr;
  input [7:0] in;
  
  always@(*) begin
    out[7:0] <= {1'b0, in[7:1]};
    cr <= 1'b0;
  end
endmodule

module ring_rt(out, cr, in);		//1-bit right Ring shifter
  output reg[7:0] out;
  output reg cr;
  input [7:0] in;
  
  always@(*) begin
    out[7:0] <= {in[0], in[7:1]};
    cr <= 1'b0;
  end
endmodule

module ring_lt(out, cr, in);		//1-bit left Ring shifter
  output reg [7:0] out;
  output reg cr;
  input [7:0] in;
  
  always@(*) begin
    out[7:0] <= {in[6:0], in[7]};
    cr <= 1'b0;
  end
endmodule

module bitw_and(out, cr, in1, in2);		//8-bit bitwise AND 
  output reg [7:0] out;
  output reg cr;
  input [7:0] in1;
  input [7:0] in2;
  
  always@(*) begin
    out <= in1 & in2;
    cr <= 1'b0;
  end
endmodule

module bitw_or(out, cr, in1, in2);		//8-bit bitwise OR
  output reg [7:0] out;
  output reg cr;
  input [7:0] in1;
  input [7:0] in2;
  
  always@(*) begin
    out <= in1 & in2;
    cr <= 1'b0;
  end
endmodule

module bitw_xor(out, cr, in1, in2);		//8-bit XOR
  output reg [7:0] out;
  output reg cr;
  input [7:0] in1;
  input [7:0] in2;
  
  always@(*) begin
    out <= in1 ^ in2;
    cr <= 1'b0;
  end
endmodule

module equl(out, cr, in1, in2);		//8-bit equality checker
  output reg [7:0] out;
  output reg cr;
  input [7:0] in1;
  input [7:0] in2;
  
  always@(*) begin
    out <= (in1==in2)?8'b00000001:8'b00000000;
    cr <= 1'b0;
  end
endmodule

module mux_8bit(out, sel, I0, I1, I2, I3, I4, I5, I6, I7, I8, I9, I10, I11, I12, I13, I14, I15);				//8-bit 16:1 MUX
  output reg [7:0] out;
  input [3:0]sel;
  input [7:0]I0, I1, I2, I3, I4, I5, I6, I7, I8, I9, I10, I11, I12, I13, I14, I15;
  
  always@(*) begin
    case(sel)
      4'b0000: out <= I0;
      4'b0001: out <= I1;
      4'b0010: out <= I2;
      4'b0011: out <= I3;
      4'b0100: out <= I4;
      4'b0101: out <= I5;
      4'b0110: out <= I6;
      4'b0111: out <= I7;
      4'b1000: out <= I8;
      4'b1001: out <= I9;
      4'b1010: out <= I10;
      4'b1011: out <= I11;
      4'b1100: out <= I12;
      4'b1101: out <= I13;
      4'b1110: out <= I14;
      4'b1111: out <= I15;
    endcase
  end
endmodule
           
module mux_1bit(out, sel, I0, I1, I2, I3, I4, I5, I6, I7, I8, I9, I10, I11, I12, I13, I14, I15);				//1 bit 16:1 MUX
  output reg out;
  input [3:0]sel;
  input I0, I1, I2, I3, I4, I5, I6, I7, I8, I9, I10, I11, I12, I13, I14, I15;
  
  always@(*) begin
    case(sel)
      4'b0000: out <= I0;
      4'b0001: out <= I1;
      4'b0010: out <= I2;
      4'b0011: out <= I3;
      4'b0100: out <= I4;
      4'b0101: out <= I5;
      4'b0110: out <= I6;
      4'b0111: out <= I7;
      4'b1000: out <= I8;
      4'b1001: out <= I9;
      4'b1010: out <= I10;
      4'b1011: out <= I11;
      4'b1100: out <= I12;
      4'b1101: out <= I13;
      4'b1110: out <= I14;
      4'b1111: out <= I15;
    endcase
  end
endmodule

testbench.sv
// Code your testbench here
// or browse Examples
module t_alu;
  wire [7:0]alu_out;
  wire carry_out;
  reg [3:0] opCode;
  reg [7:0]in_a;
  reg [7:0]in_b;
  reg clk, rst;
  
  alu_8_bit M_UUT(alu_out, carry_out, in_a, in_b, opCode, clk, rst);
  
  always
    #5 clk = ~clk;
  
  initial
    begin
      $dumpfile("aluWAVE.vcd");
      $dumpvars(0, t_alu);
      $monitor($time, " in1=%b | in2=%b | opCode=%b || cr=%b  || out=%b", in_a, in_b, opCode, carry_out, alu_out);
      in_a=8'b0; in_b=8'b0; opCode=4'b0000; clk=1'b0;
      #10 in_a=8'b10101010; in_b=8'b01010101; opCode=4'b0000;
      #10 in_a=8'b10101010; in_b=8'b01010101; opCode=4'b0001;
      #10 in_a=8'b10101010; in_b=8'b01010101; opCode=4'b0010;
      #10 in_a=8'b10101010; in_b=8'b01010101; opCode=4'b0011;
      #10 in_a=8'b10101010; in_b=8'b01010101; opCode=4'b0100;
      #10 in_a=8'b10101010; in_b=8'b01010101; opCode=4'b0101;
      #10 in_a=8'b10101010; in_b=8'b01010101; opCode=4'b0110;
      #10 in_a=8'b10101010; in_b=8'b01010101; opCode=4'b0111;
      #10 in_a=8'b10101010; in_b=8'b01010101; opCode=4'b1000;
      #10 in_a=8'b10101010; in_b=8'b01010101; opCode=4'b1001;
      #10 in_a=8'b10101010; in_b=8'b01010101; opCode=4'b1010;
      #10 in_a=8'b11100011; in_b=8'b01111101; opCode=4'b0000;
      #10 opCode=4'b0001;
      #10 in_a=8'b01111101; in_b=8'b11100011; opCode=4'b0101;
      #10 in_a=8'b11100011; in_b=8'b11100011; opCode=4'b0101;
      #10 opCode=4'b1001;
      #20 $finish;
    end
endmodule

aluWAVE.vcd
$date
	Sat Aug 22 15:13:02 2020
$end
$version
	Icarus Verilog
$end
$timescale
	1s
$end
$scope module t_alu $end
$var wire 8 ! alu_out [7:0] $end
$var wire 1 " carry_out $end
$var reg 1 # clk $end
$var reg 8 $ in_a [7:0] $end
$var reg 8 % in_b [7:0] $end
$var reg 4 & opCode [3:0] $end
$var reg 1 ' rst $end
$scope module M_UUT $end
$var wire 8 ( add_out [7:0] $end
$var wire 8 ) alu_out_temp [7:0] $end
$var wire 8 * band_out [7:0] $end
$var wire 8 + bor_out [7:0] $end
$var wire 8 , bxor_out [7:0] $end
$var wire 10 - carry [9:0] $end
$var wire 1 . carry_temp $end
$var wire 1 / clk $end
$var wire 8 0 equl_out [7:0] $end
$var wire 8 1 in_a [7:0] $end
$var wire 8 2 in_b [7:0] $end
$var wire 8 3 l_sh_out [7:0] $end
$var wire 4 4 opCode [3:0] $end
$var wire 8 5 r_sh_out [7:0] $end
$var wire 8 6 rng_l_out [7:0] $end
$var wire 8 7 rng_r_out [7:0] $end
$var wire 1 8 rst $end
$var wire 8 9 subt_out [7:0] $end
$var reg 8 : alu_out [7:0] $end
$var reg 1 ; carry_out $end
$scope module M0 $end
$var wire 8 < in1 [7:0] $end
$var wire 8 = in2 [7:0] $end
$var reg 1 > cr $end
$var reg 8 ? out [7:0] $end
$var reg 9 @ total [8:0] $end
$upscope $end
$scope module M1 $end
$var wire 8 A in1 [7:0] $end
$var wire 8 B in2 [7:0] $end
$var reg 1 C cr $end
$var reg 8 D neg_in2 [7:0] $end
$var reg 8 E out [7:0] $end
$upscope $end
$scope module M2 $end
$var wire 8 F in [7:0] $end
$var reg 1 G cr $end
$var reg 8 H out [7:0] $end
$upscope $end
$scope module M3 $end
$var wire 8 I in [7:0] $end
$var reg 1 J cr $end
$var reg 8 K out [7:0] $end
$upscope $end
$scope module M4 $end
$var wire 8 L in [7:0] $end
$var reg 1 M cr $end
$var reg 8 N out [7:0] $end
$upscope $end
$scope module M5 $end
$var wire 8 O in [7:0] $end
$var reg 1 P cr $end
$var reg 8 Q out [7:0] $end
$upscope $end
$scope module M6 $end
$var wire 8 R in1 [7:0] $end
$var wire 8 S in2 [7:0] $end
$var reg 1 T cr $end
$var reg 8 U out [7:0] $end
$upscope $end
$scope module M7 $end
$var wire 8 V in1 [7:0] $end
$var wire 8 W in2 [7:0] $end
$var reg 1 X cr $end
$var reg 8 Y out [7:0] $end
$upscope $end
$scope module M8 $end
$var wire 8 Z in1 [7:0] $end
$var wire 8 [ in2 [7:0] $end
$var reg 1 \ cr $end
$var reg 8 ] out [7:0] $end
$upscope $end
$scope module M9 $end
$var wire 8 ^ in1 [7:0] $end
$var wire 8 _ in2 [7:0] $end
$var reg 1 ` cr $end
$var reg 8 a out [7:0] $end
$upscope $end
$scope module M10 $end
$var wire 8 b I0 [7:0] $end
$var wire 8 c I1 [7:0] $end
$var wire 8 d I10 [7:0] $end
$var wire 8 e I11 [7:0] $end
$var wire 8 f I12 [7:0] $end
$var wire 8 g I13 [7:0] $end
$var wire 8 h I14 [7:0] $end
$var wire 8 i I15 [7:0] $end
$var wire 8 j I2 [7:0] $end
$var wire 8 k I3 [7:0] $end
$var wire 8 l I4 [7:0] $end
$var wire 8 m I5 [7:0] $end
$var wire 8 n I6 [7:0] $end
$var wire 8 o I7 [7:0] $end
$var wire 8 p I8 [7:0] $end
$var wire 8 q I9 [7:0] $end
$var wire 4 r sel [3:0] $end
$var reg 8 s out [7:0] $end
$upscope $end
$scope module M11 $end
$var wire 1 t I0 $end
$var wire 1 u I1 $end
$var wire 1 v I10 $end
$var wire 1 w I11 $end
$var wire 1 x I12 $end
$var wire 1 y I13 $end
$var wire 1 z I14 $end
$var wire 1 { I15 $end
$var wire 1 | I2 $end
$var wire 1 } I3 $end
$var wire 1 ~ I4 $end
$var wire 1 !" I5 $end
$var wire 1 "" I6 $end
$var wire 1 #" I7 $end
$var wire 1 $" I8 $end
$var wire 1 %" I9 $end
$var wire 4 &" sel [3:0] $end
$var reg 1 '" out $end
$upscope $end
$upscope $end
$upscope $end
$enddefinitions $end
#0
$dumpvars
0'"
b0 &"
0%"
0$"
0#"
0""
0!"
0~
0}
0|
0{
0z
0y
0x
0w
0v
0u
0t
b0 s
b0 r
b1 q
b0 p
b0 o
b0 n
b0 m
b0 l
b0 k
b0 j
b0 i
b0 h
b0 g
b0 f
b0 e
b0 d
b0 c
b0 b
b1 a
0`
b0 _
b0 ^
b0 ]
0\
b0 [
b0 Z
b0 Y
0X
b0 W
b0 V
b0 U
0T
b0 S
b0 R
b0 Q
0P
b0 O
b0 N
0M
b0 L
b0 K
0J
b0 I
b0 H
0G
b0 F
b0 E
b0 D
0C
b0 B
b0 A
b0 @
b0 ?
0>
b0 =
b0 <
x;
bx :
b0 9
x8
b0 7
b0 6
b0 5
b0 4
b0 3
b0 2
b0 1
b1 0
0/
0.
b0 -
b0 ,
b0 +
b0 *
b0 )
b0 (
x'
b0 &
b0 %
b0 $
0#
x"
bx !
$end
#5
0;
0"
b0 :
b0 !
1#
1/
#10
b11111111 s
b11111111 )
b11111111 ?
b11111111 (
b11111111 b
b11111111 ]
b11111111 ,
b11111111 p
b0 a
b0 0
b0 q
b1010100 H
b1010100 3
b1010100 j
b1010101 K
b1010101 5
b1010101 k
b1010101 N
b1010101 6
b1010101 l
b1010101 Q
b1010101 7
b1010101 m
b1010101 E
b1010101 9
b1010101 c
b10101011 D
b11111111 @
0#
0/
b1010101 %
b1010101 2
b1010101 =
b1010101 B
b1010101 S
b1010101 W
b1010101 [
b1010101 _
b10101010 $
b10101010 1
b10101010 <
b10101010 A
b10101010 F
b10101010 I
b10101010 L
b10101010 O
b10101010 R
b10101010 V
b10101010 Z
b10101010 ^
#15
b11111111 :
b11111111 !
1#
1/
#20
b1010101 s
b1010101 )
0#
0/
b1 &
b1 4
b1 r
b1 &"
#25
b1010101 :
b1010101 !
1#
1/
#30
b1010100 s
b1010100 )
0#
0/
b10 &
b10 4
b10 r
b10 &"
#35
b1010100 :
b1010100 !
1#
1/
#40
b1010101 s
b1010101 )
0#
0/
b11 &
b11 4
b11 r
b11 &"
#45
b1010101 :
b1010101 !
1#
1/
#50
0#
0/
b100 &
b100 4
b100 r
b100 &"
#55
1#
1/
#60
0#
0/
b101 &
b101 4
b101 r
b101 &"
#65
1#
1/
#70
b0 s
b0 )
0#
0/
b110 &
b110 4
b110 r
b110 &"
#75
b0 :
b0 !
1#
1/
#80
0#
0/
b111 &
b111 4
b111 r
b111 &"
#85
1#
1/
#90
b11111111 s
b11111111 )
0#
0/
b1000 &
b1000 4
b1000 r
b1000 &"
#95
b11111111 :
b11111111 !
1#
1/
#100
b0 s
b0 )
0#
0/
b1001 &
b1001 4
b1001 r
b1001 &"
#105
b0 :
b0 !
1#
1/
#110
0#
0/
b1010 &
b1010 4
b1010 r
b1010 &"
#115
1#
1/
#120
1'"
1.
1t
b1100000 ?
b1100000 (
b1100000 b
1>
b1 -
b1100000 s
b1100000 )
b10011110 ]
b10011110 ,
b10011110 p
b1100001 Y
b1100001 +
b1100001 o
b1100001 U
b1100001 *
b1100001 n
b11110001 Q
b11110001 7
b11110001 m
b11000111 N
b11000111 6
b11000111 l
b1110001 K
b1110001 5
b1110001 k
b11000110 H
b11000110 3
b11000110 j
b1100110 E
b1100110 9
b1100110 c
b10000011 D
b101100000 @
0#
0/
b0 &
b0 4
b0 r
b0 &"
b1111101 %
b1111101 2
b1111101 =
b1111101 B
b1111101 S
b1111101 W
b1111101 [
b1111101 _
b11100011 $
b11100011 1
b11100011 <
b11100011 A
b11100011 F
b11100011 I
b11100011 L
b11100011 O
b11100011 R
b11100011 V
b11100011 Z
b11100011 ^
#125
1;
1"
b1100000 :
b1100000 !
1#
1/
#130
0'"
0.
b1100110 s
b1100110 )
0#
0/
b1 &
b1 4
b1 r
b1 &"
#135
0;
0"
b1100110 :
b1100110 !
1#
1/
#140
1u
b10111110 s
b10111110 )
b11111010 H
b11111010 3
b11111010 j
b111110 K
b111110 5
b111110 k
b11111010 N
b11111010 6
b11111010 l
b10111110 Q
b10111110 7
b10111110 m
1C
b11 -
b10011010 E
b10011010 9
b10011010 c
b11101 D
0#
0/
b101 &
b101 4
b101 r
b101 &"
b11100011 %
b11100011 2
b11100011 =
b11100011 B
b11100011 S
b11100011 W
b11100011 [
b11100011 _
b1111101 $
b1111101 1
b1111101 <
b1111101 A
b1111101 F
b1111101 I
b1111101 L
b1111101 O
b1111101 R
b1111101 V
b1111101 Z
b1111101 ^
#145
b10111110 :
b10111110 !
1#
1/
#150
b11110001 s
b11110001 )
b11000110 ?
b11000110 (
b11000110 b
0u
b1 a
b1 0
b1 q
b0 ]
b0 ,
b0 p
b11100011 Y
b11100011 +
b11100011 o
b11100011 U
b11100011 *
b11100011 n
b11110001 Q
b11110001 7
b11110001 m
b11000111 N
b11000111 6
b11000111 l
b1110001 K
b1110001 5
b1110001 k
b11000110 H
b11000110 3
b11000110 j
0C
b1 -
b0 E
b0 9
b0 c
b111000110 @
0#
0/
b11100011 $
b11100011 1
b11100011 <
b11100011 A
b11100011 F
b11100011 I
b11100011 L
b11100011 O
b11100011 R
b11100011 V
b11100011 Z
b11100011 ^
#155
b11110001 :
b11110001 !
1#
1/
#160
b1 s
b1 )
0#
0/
b1001 &
b1001 4
b1001 r
b1001 &"
#165
b1 :
b1 !
1#
1/
